pandoraPlugintools/__init__.py
pandoraPlugintools/agents.py
pandoraPlugintools/discovery.py
pandoraPlugintools/encryption.py
pandoraPlugintools/general.py
pandoraPlugintools/http.py
pandoraPlugintools/modules.py
pandoraPlugintools/output.py
pandoraPlugintools/snmp.py
pandoraPlugintools/threads.py
pandoraPlugintools/transfer.py
pandoraPlugintools-1.0.4.dist-info/LICENSE
pandoraPlugintools-1.0.4.dist-info/METADATA
pandoraPlugintools-1.0.4.dist-info/WHEEL
pandoraPlugintools-1.0.4.dist-info/top_level.txt
pandoraPlugintools-1.0.4.dist-info/RECORD
