Metadata-Version: 2.1
Name: pandoraPlugintools
Version: 1.0.4
Summary: A plugin tool set of functions for pandorafms
Home-page: https://github.com/projects-pandorafms/pandoraPlugintools
Author: PandoraFMS projects department
Author-email: <projects@pandorafms.com>
Keywords: python,pandora,pandorafms,plugintool,plugintools
Classifier: Intended Audience :: Developers
Classifier: Programming Language :: Python :: 3
Classifier: Operating System :: Unix
License-File: LICENSE
Requires-Dist: datetime
Requires-Dist: cryptography (==3)
Requires-Dist: requests
Requires-Dist: requests-ntlm
Requires-Dist: pycrypto (==2.6.1)
Requires-Dist: pysnmp (==4.4.12)
